pynetics/__init__.py
pynetics/algorithm.py
pynetics/api.py
pynetics/callback.py
pynetics/exception.py
pynetics/replacement.py
pynetics/selection.py
pynetics/stop.py
pynetics/util.py
pynetics/list/__init__.py
pynetics/list/alphabet.py
pynetics/list/bin.py
pynetics/list/diversity.py
pynetics/list/exception.py
pynetics/list/genotype.py
pynetics/list/initializer.py
pynetics/list/int.py
pynetics/list/mutation.py
pynetics/list/real.py
pynetics/list/recombination.py
pynetics-0.7.0.dist-info/LICENSE.md
pynetics-0.7.0.dist-info/METADATA
pynetics-0.7.0.dist-info/WHEEL
pynetics-0.7.0.dist-info/top_level.txt
pynetics-0.7.0.dist-info/RECORD
